q5/testshiftreg.v
module myshiftreg(clk,clr,load,data,ena,A,Q,E);
 input clk,clr,A,ena,load;
 input wire [3:0] data ;
 output reg [3:0] Q;
 output reg E ;
 reg B,C,D;
 always @(posedge clk or posedge clr)
 begin 
    if(clr) begin
      Q[3:0] <= 4'b0000;
      B<=0;
      C<=0;
      D<=0;
      E<=0;
    end
    else if(load) begin 
     Q[3:0]<=data[3:0];
    end
    else if(ena) begin
     E=D;
     D=C;
     C=B;
     B=A;
    end
 end
 always @(*)
 begin 
    Q[3]=E;
    Q[2]=D;
    Q[1]=C;
    Q[0]=B;
 end 
endmodule

q5/testshiftreg_tb.v
module tb_myshiftreg;

    reg clk;
    reg clr;
    reg A;
    reg ena;
    reg load;
    reg [3:0] data;

    wire [3:0] Q;
    wire E;

    myshiftreg uut (
        .clk(clk),
        .clr(clr),
        .load(load),
        .data(data),
        .ena(ena),
        .A(A),
        .Q(Q),
        .E(E)
    );

    always begin
        #5 clk = ~clk;
    end

    initial begin
        $dumpfile("shiftreg.vcd");
        $dumpvars(0, tb_myshiftreg);

        clk = 0;
        clr = 0;
        load = 0;
        ena = 0;
        A = 0;
        data = 4'b0000;

        $monitor("Time=%0t | Q=%b | E=%b | B=%b | C=%b | D=%b | A=%b", $time, Q, E, uut.B, uut.C, uut.D, A);

        clr = 1;
        #10 clr = 0;
        
        load = 1;
        data = 4'b1101;
        #10 load = 0;

        ena = 1;
        A = 1;
        #10 ena = 0;

        ena = 1;
        A = 0;
        #10 ena = 0;

        load = 1;
        data = 4'b1010;
        #10 load = 0;

        ena = 1;
        A = 1;
        #10 ena = 0;

        clr = 1;
        #10 clr = 0;

        $finish;
    end

endmodule

q5/shiftreg.vcd
$date
	Tue Dec 31 18:48:30 2024
$end
$version
	Icarus Verilog
$end
$timescale
	1s
$end
$scope module tb_myshiftreg $end
$var wire 4 ! Q [3:0] $end
$var wire 1 " E $end
$var reg 1 # A $end
$var reg 1 $ clk $end
$var reg 1 % clr $end
$var reg 4 & data [3:0] $end
$var reg 1 ' ena $end
$var reg 1 ( load $end
$scope module uut $end
$var wire 1 # A $end
$var wire 1 $ clk $end
$var wire 1 % clr $end
$var wire 4 ) data [3:0] $end
$var wire 1 ' ena $end
$var wire 1 ( load $end
$var reg 1 * B $end
$var reg 1 + C $end
$var reg 1 , D $end
$var reg 1 " E $end
$var reg 4 - Q [3:0] $end
$upscope $end
$upscope $end
$enddefinitions $end
$comment Show the parameter values. $end
$dumpall
$end
#0
$dumpvars
b0 -
0,
0+
0*
b0 )
0(
0'
b0 &
1%
0$
0#
0"
b0 !
$end
#5
1$
#10
0$
b1101 &
b1101 )
1(
0%
#15
b1101 !
b1101 -
1$
#20
0$
1#
1'
0(
#25
b1 !
b1 -
1*
1$
#30
0$
0#
1'
#35
b10 !
b10 -
0*
1+
1$
#40
0$
b1010 &
b1010 )
1(
0'
#45
b1010 !
b1010 -
1$
#50
0$
1#
1'
0(
#55
b101 !
b101 -
1*
0+
1,
1$
#60
0,
0*
b0 !
b0 -
0$
1%
0'
#65
1$
#70
0$
0%
