q2/dffset.v
module testfile (
    input wire D,     
    input wire clk,   
    input wire clear, 
    output reg Q     
);
    initial begin
        Q = 0; // Set initial value of Q
    end

    always @(posedge clk or posedge clear) begin
        if (clear)
            Q <= 1'b0;  
        else
            Q <= D;    
    end
endmodule

module dffset(
    input wire D,
    input wire clk,
    input wire set,
    output reg Q
);
    wire f;

    // Instantiate the testfile submodule
    testfile t5 (
        .D(D),
        .clk(clk),
        .clear(1'b0), // Hardwired clear to 0
        .Q(f)
    );

   
    always @(posedge clk or posedge set) 
      begin
        if (set) 
            Q <= 1'b1;
        else 
            Q <= f;    
      end
endmodule

q2/testfile_tb.v
`timescale 1ns/1ps

module testfile_tb;

    reg D, clk, clear; // Inputs to the flip-flop
    wire Q;             // Output of the flip-flop

    // Instantiate the testfile module
    testfile uut (
        .D(D),
        .clk(clk),
        .clear(clear),
        .Q(Q)
    );

    // Clock generation (50 MHz)
    initial begin
        clk = 0;
        forever #5 clk = ~clk; // Toggle clock every 10ns
    end

    // Stimulus
    initial begin
        // Initialize inputs
        D = 0; clear = 0;

        // Test case 1: Normal operation
        #15 D = 1;
        #20 D = 0;

        // Test case 2: Clear operation
        #25 clear = 1; // Assert clear
        #10 clear = 0; // Deassert clear

        // Test case 3: D = 1 and clear = 1
        #10 D = 1; clear = 1; // Both D and clear are 1
        #10 clear = 0; // Deassert clear

        // Test case 4: Normal operation resumes
        #15 D = 1;

        // Finish simulation after 100ns
        #100 $finish;
    end

    // Monitor changes
    initial begin
        $monitor("Time: %0dns | D = %b | clk = %b | clear = %b | Q = %b", $time, D, clk, clear, Q);
    end

    // Generate VCD file
    initial begin
        $dumpfile("testfile_tb.vcd"); // Specify the name of the VCD file
        $dumpvars(0, testfile_tb);    // Dump all variables in the testbench
    end

endmodule

q2/testfile_tb.vcd
$date
	Sun Dec 29 15:20:49 2024
$end
$version
	Icarus Verilog
$end
$timescale
	1ps
$end
$scope module testfile_tb $end
$var wire 1 ! Q $end
$var reg 1 " D $end
$var reg 1 # clear $end
$var reg 1 $ clk $end
$scope module uut $end
$var wire 1 " D $end
$var wire 1 # clear $end
$var wire 1 $ clk $end
$var reg 1 ! Q $end
$upscope $end
$upscope $end
$scope module testfile_tb $end
$scope module uut $end
$upscope $end
$upscope $end
$enddefinitions $end
$comment Show the parameter values. $end
$dumpall
$end
#0
$dumpvars
0$
0#
0"
0!
$end
#5000
1$
#10000
0$
#15000
1!
1$
1"
#20000
0$
#25000
1$
#30000
0$
#35000
0!
1$
0"
#40000
0$
#45000
1$
#50000
0$
#55000
1$
#60000
0$
1#
#65000
1$
#70000
0$
0#
#75000
1$
#80000
0$
1#
1"
#85000
1$
#90000
0$
0#
#95000
1!
1$
